Workbook

Sheet 📋 Parametri
B1: ☀ ANALISI AMMORTAMENTO IMPIANTO FOTOVOLTAICO
B2: Modifica i valori in BLU per personalizzare l'analisi
B4: IMPIANTO
B5: Potenza installata (kWp) | C5: 6 | D5: Kilowatt-picco totali installati
B6: Esposizione (1=Sud … vedi tabella) | C6: 1 | D6: Fattore da tabella Riferimento (1.0=Sud, 0.74=Est)
B7: Ore picco equivalenti (h/anno) | C7: 1200 | D7: Nord IT: 1150 | Centro: 1350 | Sud: 1500 | Sicilia: 1600
B8: Performance Ratio | C8: 0.8 | D8: Perdite reali: cablaggio, calore, inverter (0.75–0.85)
B9: Degrado annuo pannelli | C9: 0.005 | D9: Perdita efficienza/anno composta (0.4–0.8%)
B10: COSTI
B11: Costo impianto (€) | C11: 12000 | D11: Pannelli + inverter + struttura + manodopera
B12: Costo batteria/accumulo (€) | C12: 0 | D12: 0 se non presente. Indicativo: ~600 €/kWh capacità
B13: Manutenzione annua (€) | C13: =C5*20 -> 120 | D13: Pulizia, assicurazione, piccoli interventi
B14: Anno sostituzione inverter | C14: 13 | D14: Vita media inverter: 10–15 anni
B15: Costo sostituzione inverter (€) | C15: =C5*200 -> 1200 | D15: Indicativo: 150–300 €/kWp
B16: ENERGIA
B17: Prezzo acquisto energia (€/kWh) | C17: 0.25 | D17: Tariffa in bolletta incl. oneri e tasse
B18: Prezzo vendita energia (€/kWh) | C18: 0.1 | D18: Ritiro dedicato GSE (tipico: 0.05–0.12 €/kWh)
B19: Autoconsumo (%) | C19: 0.45 | D19: Quota produzione usata in casa (senza batt: 25–45%)
B20: Incremento annuo prezzo energia | C20: 0.03 | D20: Aumento annuo atteso (storico EU: 3–5%)
B21: INCENTIVI & FINANZA
B22: Aliquota detrazione IRPEF (%) | C22: 0.5 | D22: 50% (attuale IT) oppure 36% → 0 per nessun incent.
B23: Anni detrazione | C23: 10 | D23: Periodo di detrazione (normalmente 10 anni)
B24: Tasso di sconto (WACC / opport.) | C24: 0.03 | D24: Costo opportunità capitale per NPV (2–4%)
B25: Orizzonte analisi (anni) | C25: 25 | D25: Vita utile tipica pannelli: 25–30 anni
B27: LEGENDA COLORI
B28: Esempio | C28: 123 | D28: Cella di INPUT (testo blu) — inserisci il tuo valore
B29: Esempio | C29: 123 | D29: Risultato calcolato — si aggiorna automaticamente

Sheet 📊 Modello Annuale
A1: MODELLO FINANZIARIO ANNUALE — IMPIANTO FOTOVOLTAICO
B2: PRODUZIONE (kWh) | E2: PREZZI (€/kWh) | G2: RICAVI (€) | J2: COSTI (€) | L2: FLUSSI CASSA (€) | N2: FLUSSI ATTUALIZZATI (€)
A3: Anno | B3: Tot. Prodotta | C3: Autoconsumata | D3: Immessa Rete | E3: P. Acquisto | F3: P. Vendita | G3: Risp. Autocons. | H3: Ric. Immissione | I3: Beneficio Lordo | J3: Incentivo Fisc. | K3: Costi Oper. | L3: Flusso Netto | M3: Flusso Cumulato | N3: Flusso Att. | O3: Flusso Att. Cum. | P3: Flussi IRR
A4: 1 | B4: ='📋 Parametri'!C5*'📋 Parametri'!C7*'📋 Parametri'!C6*'📋 Parametri'!C8*(1-'📋 Parametri'!C9)^(1-1) -> 5760 | C4: =B4*'📋 Parametri'!C19 -> 2592 | D4: =B4-C4 -> 3168 | E4: ='📋 Parametri'!C17*(1+'📋 Parametri'!C20)^(1-1) -> 0.25 | F4: ='📋 Parametri'!C18*(1+'📋 Parametri'!C20)^(1-1) -> 0.1 | G4: =C4*E4 -> 648 | H4: =D4*F4 -> 316.8 | I4: =G4+H4 -> 964.8 | J4: =IF(AND(1>=1,1<='📋 Parametri'!C23),'📋 Parametri'!C11*'📋 Parametri'!C22/'📋 Parametri'!C23,0) -> 600 | K4: ='📋 Parametri'!C13+IF(1='📋 Parametri'!C14,'📋 Parametri'!C15,0) -> 120 | L4: =I4+J4-K4 -> 1444.8 | M4: =-('📋 Parametri'!C11+'📋 Parametri'!C12)+L4 -> -10555.2 | N4: =L4/(1+'📋 Parametri'!C24)^1 -> 1402.7184 | O4: =-('📋 Parametri'!C11+'📋 Parametri'!C12)+N4 -> -10597.282 | P4: =-('📋 Parametri'!C11+'📋 Parametri'!C12)+L4 -> -10555.2
A5: 2 | B5: ='📋 Parametri'!C5*'📋 Parametri'!C7*'📋 Parametri'!C6*'📋 Parametri'!C8*(1-'📋 Parametri'!C9)^(2-1) -> 5731.2 | C5: =B5*'📋 Parametri'!C19 -> 2579.04 | D5: =B5-C5 -> 3152.16 | E5: ='📋 Parametri'!C17*(1+'📋 Parametri'!C20)^(2-1) -> 0.2575 | F5: ='📋 Parametri'!C18*(1+'📋 Parametri'!C20)^(2-1) -> 0.103 | G5: =C5*E5 -> 664.1028 | H5: =D5*F5 -> 324.67248 | I5: =G5+H5 -> 988.77528 | J5: =IF(AND(2>=1,2<='📋 Parametri'!C23),'📋 Parametri'!C11*'📋 Parametri'!C22/'📋 Parametri'!C23,0) -> 600 | K5: ='📋 Parametri'!C13+IF(2='📋 Parametri'!C14,'📋 Parametri'!C15,0) -> 120 | L5: =I5+J5-K5 -> 1468.7753 | M5: =M4+L5 -> -9086.4247 | N5: =L5/(1+'📋 Parametri'!C24)^2 -> 1384.4616 | O5: =O4+N5 -> -9212.82 | P5: =L5 -> 1468.7753
A6: 3 | B6: ='📋 Parametri'!C5*'📋 Parametri'!C7*'📋 Parametri'!C6*'📋 Parametri'!C8*(1-'📋 Parametri'!C9)^(3-1) -> 5702.544 | C6: =B6*'📋 Parametri'!C19 -> 2566.1448 | D6: =B6-C6 -> 3136.3992 | E6: ='📋 Parametri'!C17*(1+'📋 Parametri'!C20)^(3-1) -> 0.265225 | F6: ='📋 Parametri'!C18*(1+'📋 Parametri'!C20)^(3-1) -> 0.10609 | G6: =C6*E6 -> 680.60575 | H6: =D6*F6 -> 332.74059 | I6: =G6+H6 -> 1013.3463 | J6: =IF(AND(3>=1,3<='📋 Parametri'!C23),'📋 Parametri'!C11*'📋 Parametri'!C22/'📋 Parametri'!C23,0) -> 600 | K6: ='📋 Parametri'!C13+IF(3='📋 Parametri'!C14,'📋 Parametri'!C15,0) -> 120 | L6: =I6+J6-K6 -> 1493.3463 | M6: =M5+L6 -> -7593.0784 | N6: =L6/(1+'📋 Parametri'!C24)^3 -> 1366.6235 | O6: =O5+N6 -> -7846.1965 | P6: =L6 -> 1493.3463
A7: 4 | B7: ='📋 Parametri'!C5*'📋 Parametri'!C7*'📋 Parametri'!C6*'📋 Parametri'!C8*(1-'📋 Parametri'!C9)^(4-1) -> 5674.0313 | C7: =B7*'📋 Parametri'!C19 -> 2553.3141 | D7: =B7-C7 -> 3120.7172 | E7: ='📋 Parametri'!C17*(1+'📋 Parametri'!C20)^(4-1) -> 0.27318175 | F7: ='📋 Parametri'!C18*(1+'📋 Parametri'!C20)^(4-1) -> 0.1092727 | G7: =C7*E7 -> 697.51881 | H7: =D7*F7 -> 341.00919 | I7: =G7+H7 -> 1038.528 | J7: =IF(AND(4>=1,4<='📋 Parametri'!C23),'📋 Parametri'!C11*'📋 Parametri'!C22/'📋 Parametri'!C23,0) -> 600 | K7: ='📋 Parametri'!C13+IF(4='📋 Parametri'!C14,'📋 Parametri'!C15,0) -> 120 | L7: =I7+J7-K7 -> 1518.528 | M7: =M6+L7 -> -6074.5504 | N7: =L7/(1+'📋 Parametri'!C24)^4 -> 1349.1925 | O7: =O6+N7 -> -6497.0041 | P7: =L7 -> 1518.528
A8: 5 | B8: ='📋 Parametri'!C5*'📋 Parametri'!C7*'📋 Parametri'!C6*'📋 Parametri'!C8*(1-'📋 Parametri'!C9)^(5-1) -> 5645.6611 | C8: =B8*'📋 Parametri'!C19 -> 2540.5475 | D8: =B8-C8 -> 3105.1136 | E8: ='📋 Parametri'!C17*(1+'📋 Parametri'!C20)^(5-1) -> 0.2813772 | F8: ='📋 Parametri'!C18*(1+'📋 Parametri'!C20)^(5-1) -> 0.11255088 | G8: =C8*E8 -> 714.85215 | H8: =D8*F8 -> 349.48327 | I8: =G8+H8 -> 1064.3354 | J8: =IF(AND(5>=1,5<='📋 Parametri'!C23),'📋 Parametri'!C11*'📋 Parametri'!C22/'📋 Parametri'!C23,0) -> 600 | K8: ='📋 Parametri'!C13+IF(5='📋 Parametri'!C14,'📋 Parametri'!C15,0) -> 120 | L8: =I8+J8-K8 -> 1544.3354 | M8: =M7+L8 -> -4530.2149 | N8: =L8/(1+'📋 Parametri'!C24)^5 -> 1332.1573 | O8: =O7+N8 -> -5164.8468 | P8: =L8 -> 1544.3354
A9: 6 | B9: ='📋 Parametri'!C5*'📋 Parametri'!C7*'📋 Parametri'!C6*'📋 Parametri'!C8*(1-'📋 Parametri'!C9)^(6-1) -> 5617.4328 | C9: =B9*'📋 Parametri'!C19 -> 2527.8448 | D9: =B9-C9 -> 3089.588 | E9: ='📋 Parametri'!C17*(1+'📋 Parametri'!C20)^(6-1) -> 0.28981852 | F9: ='📋 Parametri'!C18*(1+'📋 Parametri'!C20)^(6-1) -> 0.11592741 | G9: =C9*E9 -> 732.61623 | H9: =D9*F9 -> 358.16793 | I9: =G9+H9 -> 1090.7842 | J9: =IF(AND(6>=1,6<='📋 Parametri'!C23),'📋 Parametri'!C11*'📋 Parametri'!C22/'📋 Parametri'!C23,0) -> 600 | K9: ='📋 Parametri'!C13+IF(6='📋 Parametri'!C14,'📋 Parametri'!C15,0) -> 120 | L9: =I9+J9-K9 -> 1570.7842 | M9: =M8+L9 -> -2959.4308 | N9: =L9/(1+'📋 Parametri'!C24)^6 -> 1315.507 | O9: =O8+N9 -> -3849.3398 | P9: =L9 -> 1570.7842
A10: 7 | B10: ='📋 Parametri'!C5*'📋 Parametri'!C7*'📋 Parametri'!C6*'📋 Parametri'!C8*(1-'📋 Parametri'!C9)^(7-1) -> 5589.3457 | C10: =B10*'📋 Parametri'!C19 -> 2515.2055 | D10: =B10-C10 -> 3074.1401 | E10: ='📋 Parametri'!C17*(1+'📋 Parametri'!C20)^(7-1) -> 0.29851307 | F10: ='📋 Parametri'!C18*(1+'📋 Parametri'!C20)^(7-1) -> 0.11940523 | G10: =C10*E10 -> 750.82174 | H10: =D10*F10 -> 367.06841 | I10: =G10+H10 -> 1117.8901 | J10: =IF(AND(7>=1,7<='📋 Parametri'!C23),'📋 Parametri'!C11*'📋 Parametri'!C22/'📋 Parametri'!C23,0) -> 600 | K10: ='📋 Parametri'!C13+IF(7='📋 Parametri'!C14,'📋 Parametri'!C15,0) -> 120 | L10: =I10+J10-K10 -> 1597.8901 | M10: =M9+L10 -> -1361.5406 | N10: =L10/(1+'📋 Parametri'!C24)^7 -> 1299.2309 | O10: =O9+N10 -> -2550.1088 | P10: =L10 -> 1597.8901
A11: 8 | B11: ='📋 Parametri'!C5*'📋 Parametri'!C7*'📋 Parametri'!C6*'📋 Parametri'!C8*(1-'📋 Parametri'!C9)^(8-1) -> 5561.3989 | C11: =B11*'📋 Parametri'!C19 -> 2502.6295 | D11: =B11-C11 -> 3058.7694 | E11: ='📋 Parametri'!C17*(1+'📋 Parametri'!C20)^(8-1) -> 0.30746847 | F11: ='📋 Parametri'!C18*(1+'📋 Parametri'!C20)^(8-1) -> 0.12298739 | G11: =C11*E11 -> 769.47966 | H11: =D11*F11 -> 376.19006 | I11: =G11+H11 -> 1145.6697 | J11: =IF(AND(8>=1,8<='📋 Parametri'!C23),'📋 Parametri'!C11*'📋 Parametri'!C22/'📋 Parametri'!C23,0) -> 600 | K11: ='📋 Parametri'!C13+IF(8='📋 Parametri'!C14,'📋 Parametri'!C15,0) -> 120 | L11: =I11+J11-K11 -> 1625.6697 | M11: =M10+L11 -> 264.12907 | N11: =L11/(1+'📋 Parametri'!C24)^8 -> 1283.3187 | O11: =O10+N11 -> -1266.7902 | P11: =L11 -> 1625.6697
A12: 9 | B12: ='📋 Parametri'!C5*'📋 Parametri'!C7*'📋 Parametri'!C6*'📋 Parametri'!C8*(1-'📋 Parametri'!C9)^(9-1) -> 5533.5919 | C12: =B12*'📋 Parametri'!C19 -> 2490.1164 | D12: =B12-C12 -> 3043.4756 | E12: ='📋 Parametri'!C17*(1+'📋 Parametri'!C20)^(9-1) -> 0.31669252 | F12: ='📋 Parametri'!C18*(1+'📋 Parametri'!C20)^(9-1) -> 0.12667701 | G12: =C12*E12 -> 788.60123 | H12: =D12*F12 -> 385.53838 | I12: =G12+H12 -> 1174.1396 | J12: =IF(AND(9>=1,9<='📋 Parametri'!C23),'📋 Parametri'!C11*'📋 Parametri'!C22/'📋 Parametri'!C23,0) -> 600 | K12: ='📋 Parametri'!C13+IF(9='📋 Parametri'!C14,'📋 Parametri'!C15,0) -> 120 | L12: =I12+J12-K12 -> 1654.1396 | M12: =M11+L12 -> 1918.2687 | N12: =L12/(1+'📋 Parametri'!C24)^9 -> 1267.7603 | O12: =O11+N12 -> 0.97010787 | P12: =L12 -> 1654.1396
A13: 10 | B13: ='📋 Parametri'!C5*'📋 Parametri'!C7*'📋 Parametri'!C6*'📋 Parametri'!C8*(1-'📋 Parametri'!C9)^(10-1) -> 5505.924 | C13: =B13*'📋 Parametri'!C19 -> 2477.6658 | D13: =B13-C13 -> 3028.2582 | E13: ='📋 Parametri'!C17*(1+'📋 Parametri'!C20)^(10-1) -> 0.3261933 | F13: ='📋 Parametri'!C18*(1+'📋 Parametri'!C20)^(10-1) -> 0.13047732 | G13: =C13*E13 -> 808.19797 | H13: =D13*F13 -> 395.11901 | I13: =G13+H13 -> 1203.317 | J13: =IF(AND(10>=1,10<='📋 Parametri'!C23),'📋 Parametri'!C11*'📋 Parametri'!C22/'📋 Parametri'!C23,0) -> 600 | K13: ='📋 Parametri'!C13+IF(10='📋 Parametri'!C14,'📋 Parametri'!C15,0) -> 120 | L13: =I13+J13-K13 -> 1683.317 | M13: =M12+L13 -> 3601.5857 | N13: =L13/(1+'📋 Parametri'!C24)^10 -> 1252.5459 | O13: =O12+N13 -> 1253.516 | P13: =L13 -> 1683.317
A14: 11 | B14: ='📋 Parametri'!C5*'📋 Parametri'!C7*'📋 Parametri'!C6*'📋 Parametri'!C8*(1-'📋 Parametri'!C9)^(11-1) -> 5478.3944 | C14: =B14*'📋 Parametri'!C19 -> 2465.2775 | D14: =B14-C14 -> 3013.1169 | E14: ='📋 Parametri'!C17*(1+'📋 Parametri'!C20)^(11-1) -> 0.33597909 | F14: ='📋 Parametri'!C18*(1+'📋 Parametri'!C20)^(11-1) -> 0.13439164 | G14: =C14*E14 -> 828.28169 | H14: =D14*F14 -> 404.93771 | I14: =G14+H14 -> 1233.2194 | J14: =IF(AND(11>=1,11<='📋 Parametri'!C23),'📋 Parametri'!C11*'📋 Parametri'!C22/'📋 Parametri'!C23,0) -> 0 | K14: ='📋 Parametri'!C13+IF(11='📋 Parametri'!C14,'📋 Parametri'!C15,0) -> 120 | L14: =I14+J14-K14 -> 1113.2194 | M14: =M13+L14 -> 4714.8051 | N14: =L14/(1+'📋 Parametri'!C24)^11 -> 804.21338 | O14: =O13+N14 -> 2057.7294 | P14: =L14 -> 1113.2194
A15: 12 | B15: ='📋 Parametri'!C5*'📋 Parametri'!C7*'📋 Parametri'!C6*'📋 Parametri'!C8*(1-'📋 Parametri'!C9)^(12-1) -> 5451.0024 | C15: =B15*'📋 Parametri'!C19 -> 2452.9511 | D15: =B15-C15 -> 2998.0513 | E15: ='📋 Parametri'!C17*(1+'📋 Parametri'!C20)^(12-1) -> 0.34605847 | F15: ='📋 Parametri'!C18*(1+'📋 Parametri'!C20)^(12-1) -> 0.13842339 | G15: =C15*E15 -> 848.86449 | H15: =D15*F15 -> 415.00042 | I15: =G15+H15 -> 1263.8649 | J15: =IF(AND(12>=1,12<='📋 Parametri'!C23),'📋 Parametri'!C11*'📋 Parametri'!C22/'📋 Parametri'!C23,0) -> 0 | K15: ='📋 Parametri'!C13+IF(12='📋 Parametri'!C14,'📋 Parametri'!C15,0) -> 120 | L15: =I15+J15-K15 -> 1143.8649 | M15: =M14+L15 -> 5858.67 | N15: =L15/(1+'📋 Parametri'!C24)^12 -> 802.28383 | O15: =O14+N15 -> 2860.0132 | P15: =L15 -> 1143.8649
A16: 13 | B16: ='📋 Parametri'!C5*'📋 Parametri'!C7*'📋 Parametri'!C6*'📋 Parametri'!C8*(1-'📋 Parametri'!C9)^(13-1) -> 5423.7474 | C16: =B16*'📋 Parametri'!C19 -> 2440.6863 | D16: =B16-C16 -> 2983.0611 | E16: ='📋 Parametri'!C17*(1+'📋 Parametri'!C20)^(13-1) -> 0.35644022 | F16: ='📋 Parametri'!C18*(1+'📋 Parametri'!C20)^(13-1) -> 0.14257609 | G16: =C16*E16 -> 869.95877 | H16: =D16*F16 -> 425.31318 | I16: =G16+H16 -> 1295.2719 | J16: =IF(AND(13>=1,13<='📋 Parametri'!C23),'📋 Parametri'!C11*'📋 Parametri'!C22/'📋 Parametri'!C23,0) -> 0 | K16: ='📋 Parametri'!C13+IF(13='📋 Parametri'!C14,'📋 Parametri'!C15,0) -> 1320 | L16: =I16+J16-K16 -> -24.728051 | M16: =M15+L16 -> 5833.9419 | N16: =L16/(1+'📋 Parametri'!C24)^13 -> -16.8386 | O16: =O15+N16 -> 2843.1746 | P16: =L16 -> -24.728051
A17: 14 | B17: ='📋 Parametri'!C5*'📋 Parametri'!C7*'📋 Parametri'!C6*'📋 Parametri'!C8*(1-'📋 Parametri'!C9)^(14-1) -> 5396.6286 | C17: =B17*'📋 Parametri'!C19 -> 2428.4829 | D17: =B17-C17 -> 2968.1457 | E17: ='📋 Parametri'!C17*(1+'📋 Parametri'!C20)^(14-1) -> 0.36713343 | F17: ='📋 Parametri'!C18*(1+'📋 Parametri'!C20)^(14-1) -> 0.14685337 | G17: =C17*E17 -> 891.57725 | H17: =D17*F17 -> 435.88221 | I17: =G17+H17 -> 1327.4595 | J17: =IF(AND(14>=1,14<='📋 Parametri'!C23),'📋 Parametri'!C11*'📋 Parametri'!C22/'📋 Parametri'!C23,0) -> 0 | K17: ='📋 Parametri'!C13+IF(14='📋 Parametri'!C14,'📋 Parametri'!C15,0) -> 120 | L17: =I17+J17-K17 -> 1207.4595 | M17: =M16+L17 -> 7041.4014 | N17: =L17/(1+'📋 Parametri'!C24)^14 -> 798.27295 | O17: =O16+N17 -> 3641.4476 | P17: =L17 -> 1207.4595
A18: 15 | B18: ='📋 Parametri'!C5*'📋 Parametri'!C7*'📋 Parametri'!C6*'📋 Parametri'!C8*(1-'📋 Parametri'!C9)^(15-1) -> 5369.6455 | C18: =B18*'📋 Parametri'!C19 -> 2416.3405 | D18: =B18-C18 -> 2953.305 | E18: ='📋 Parametri'!C17*(1+'📋 Parametri'!C20)^(15-1) -> 0.37814743 | F18: ='📋 Parametri'!C18*(1+'📋 Parametri'!C20)^(15-1) -> 0.15125897 | G18: =C18*E18 -> 913.73294 | H18: =D18*F18 -> 446.71388 | I18: =G18+H18 -> 1360.4468 | J18: =IF(AND(15>=1,15<='📋 Parametri'!C23),'📋 Parametri'!C11*'📋 Parametri'!C22/'📋 Parametri'!C23,0) -> 0 | K18: ='📋 Parametri'!C13+IF(15='📋 Parametri'!C14,'📋 Parametri'!C15,0) -> 120 | L18: =I18+J18-K18 -> 1240.4468 | M18: =M17+L18 -> 8281.8482 | N18: =L18/(1+'📋 Parametri'!C24)^15 -> 796.19561 | O18: =O17+N18 -> 4437.6432 | P18: =L18 -> 1240.4468
A19: 16 | B19: ='📋 Parametri'!C5*'📋 Parametri'!C7*'📋 Parametri'!C6*'📋 Parametri'!C8*(1-'📋 Parametri'!C9)^(16-1) -> 5342.7973 | C19: =B19*'📋 Parametri'!C19 -> 2404.2588 | D19: =B19-C19 -> 2938.5385 | E19: ='📋 Parametri'!C17*(1+'📋 Parametri'!C20)^(16-1) -> 0.38949185 | F19: ='📋 Parametri'!C18*(1+'📋 Parametri'!C20)^(16-1) -> 0.15579674 | G19: =C19*E19 -> 936.43921 | H19: =D19*F19 -> 457.81472 | I19: =G19+H19 -> 1394.2539 | J19: =IF(AND(16>=1,16<='📋 Parametri'!C23),'📋 Parametri'!C11*'📋 Parametri'!C22/'📋 Parametri'!C23,0) -> 0 | K19: ='📋 Parametri'!C13+IF(16='📋 Parametri'!C14,'📋 Parametri'!C15,0) -> 120 | L19: =I19+J19-K19 -> 1274.2539 | M19: =M18+L19 -> 9556.1021 | N19: =L19/(1+'📋 Parametri'!C24)^16 -> 794.07292 | O19: =O18+N19 -> 5231.7161 | P19: =L19 -> 1274.2539
A20: 17 | B20: ='📋 Parametri'!C5*'📋 Parametri'!C7*'📋 Parametri'!C6*'📋 Parametri'!C8*(1-'📋 Parametri'!C9)^(17-1) -> 5316.0833 | C20: =B20*'📋 Parametri'!C19 -> 2392.2375 | D20: =B20-C20 -> 2923.8458 | E20: ='📋 Parametri'!C17*(1+'📋 Parametri'!C20)^(17-1) -> 0.40117661 | F20: ='📋 Parametri'!C18*(1+'📋 Parametri'!C20)^(17-1) -> 0.16047064 | G20: =C20*E20 -> 959.70972 | H20: =D20*F20 -> 469.19142 | I20: =G20+H20 -> 1428.9011 | J20: =IF(AND(17>=1,17<='📋 Parametri'!C23),'📋 Parametri'!C11*'📋 Parametri'!C22/'📋 Parametri'!C23,0) -> 0 | K20: ='📋 Parametri'!C13+IF(17='📋 Parametri'!C14,'📋 Parametri'!C15,0) -> 120 | L20: =I20+J20-K20 -> 1308.9011 | M20: =M19+L20 -> 10865.003 | N20: =L20/(1+'📋 Parametri'!C24)^17 -> 791.90671 | O20: =O19+N20 -> 6023.6228 | P20: =L20 -> 1308.9011
A21: 18 | B21: ='📋 Parametri'!C5*'📋 Parametri'!C7*'📋 Parametri'!C6*'📋 Parametri'!C8*(1-'📋 Parametri'!C9)^(18-1) -> 5289.5029 | C21: =B21*'📋 Parametri'!C19 -> 2380.2763 | D21: =B21-C21 -> 2909.2266 | E21: ='📋 Parametri'!C17*(1+'📋 Parametri'!C20)^(18-1) -> 0.41321191 | F21: ='📋 Parametri'!C18*(1+'📋 Parametri'!C20)^(18-1) -> 0.16528476 | G21: =C21*E21 -> 983.55851 | H21: =D21*F21 -> 480.85083 | I21: =G21+H21 -> 1464.4093 | J21: =IF(AND(18>=1,18<='📋 Parametri'!C23),'📋 Parametri'!C11*'📋 Parametri'!C22/'📋 Parametri'!C23,0) -> 0 | K21: ='📋 Parametri'!C13+IF(18='📋 Parametri'!C14,'📋 Parametri'!C15,0) -> 120 | L21: =I21+J21-K21 -> 1344.4093 | M21: =M20+L21 -> 12209.413 | N21: =L21/(1+'📋 Parametri'!C24)^18 -> 789.69879 | O21: =O20+N21 -> 6813.3216 | P21: =L21 -> 1344.4093
A22: 19 | B22: ='📋 Parametri'!C5*'📋 Parametri'!C7*'📋 Parametri'!C6*'📋 Parametri'!C8*(1-'📋 Parametri'!C9)^(19-1) -> 5263.0553 | C22: =B22*'📋 Parametri'!C19 -> 2368.3749 | D22: =B22-C22 -> 2894.6804 | E22: ='📋 Parametri'!C17*(1+'📋 Parametri'!C20)^(19-1) -> 0.42560827 | F22: ='📋 Parametri'!C18*(1+'📋 Parametri'!C20)^(19-1) -> 0.17024331 | G22: =C22*E22 -> 1007.9999 | H22: =D22*F22 -> 492.79997 | I22: =G22+H22 -> 1500.7999 | J22: =IF(AND(19>=1,19<='📋 Parametri'!C23),'📋 Parametri'!C11*'📋 Parametri'!C22/'📋 Parametri'!C23,0) -> 0 | K22: ='📋 Parametri'!C13+IF(19='📋 Parametri'!C14,'📋 Parametri'!C15,0) -> 120 | L22: =I22+J22-K22 -> 1380.7999 | M22: =M21+L22 -> 13590.212 | N22: =L22/(1+'📋 Parametri'!C24)^19 -> 787.45089 | O22: =O21+N22 -> 7600.7725 | P22: =L22 -> 1380.7999
A23: 20 | B23: ='📋 Parametri'!C5*'📋 Parametri'!C7*'📋 Parametri'!C6*'📋 Parametri'!C8*(1-'📋 Parametri'!C9)^(20-1) -> 5236.7401 | C23: =B23*'📋 Parametri'!C19 -> 2356.533 | D23: =B23-C23 -> 2880.207 | E23: ='📋 Parametri'!C17*(1+'📋 Parametri'!C20)^(20-1) -> 0.43837651 | F23: ='📋 Parametri'!C18*(1+'📋 Parametri'!C20)^(20-1) -> 0.17535061 | G23: =C23*E23 -> 1033.0487 | H23: =D23*F23 -> 505.04605 | I23: =G23+H23 -> 1538.0948 | J23: =IF(AND(20>=1,20<='📋 Parametri'!C23),'📋 Parametri'!C11*'📋 Parametri'!C22/'📋 Parametri'!C23,0) -> 0 | K23: ='📋 Parametri'!C13+IF(20='📋 Parametri'!C14,'📋 Parametri'!C15,0) -> 120 | L23: =I23+J23-K23 -> 1418.0948 | M23: =M22+L23 -> 15008.307 | N23: =L23/(1+'📋 Parametri'!C24)^20 -> 785.1647 | O23: =O22+N23 -> 8385.9372 | P23: =L23 -> 1418.0948
A24: 21 | B24: ='📋 Parametri'!C5*'📋 Parametri'!C7*'📋 Parametri'!C6*'📋 Parametri'!C8*(1-'📋 Parametri'!C9)^(21-1) -> 5210.5564 | C24: =B24*'📋 Parametri'!C19 -> 2344.7504 | D24: =B24-C24 -> 2865.806 | E24: ='📋 Parametri'!C17*(1+'📋 Parametri'!C20)^(21-1) -> 0.45152781 | F24: ='📋 Parametri'!C18*(1+'📋 Parametri'!C20)^(21-1) -> 0.18061112 | G24: =C24*E24 -> 1058.72 | H24: =D24*F24 -> 517.59644 | I24: =G24+H24 -> 1576.3164 | J24: =IF(AND(21>=1,21<='📋 Parametri'!C23),'📋 Parametri'!C11*'📋 Parametri'!C22/'📋 Parametri'!C23,0) -> 0 | K24: ='📋 Parametri'!C13+IF(21='📋 Parametri'!C14,'📋 Parametri'!C15,0) -> 120 | L24: =I24+J24-K24 -> 1456.3164 | M24: =M23+L24 -> 16464.624 | N24: =L24/(1+'📋 Parametri'!C24)^21 -> 782.84185 | O24: =O23+N24 -> 9168.7791 | P24: =L24 -> 1456.3164
A25: 22 | B25: ='📋 Parametri'!C5*'📋 Parametri'!C7*'📋 Parametri'!C6*'📋 Parametri'!C8*(1-'📋 Parametri'!C9)^(22-1) -> 5184.5036 | C25: =B25*'📋 Parametri'!C19 -> 2333.0266 | D25: =B25-C25 -> 2851.477 | E25: ='📋 Parametri'!C17*(1+'📋 Parametri'!C20)^(22-1) -> 0.46507364 | F25: ='📋 Parametri'!C18*(1+'📋 Parametri'!C20)^(22-1) -> 0.18602946 | G25: =C25*E25 -> 1085.0292 | H25: =D25*F25 -> 530.45871 | I25: =G25+H25 -> 1615.4879 | J25: =IF(AND(22>=1,22<='📋 Parametri'!C23),'📋 Parametri'!C11*'📋 Parametri'!C22/'📋 Parametri'!C23,0) -> 0 | K25: ='📋 Parametri'!C13+IF(22='📋 Parametri'!C14,'📋 Parametri'!C15,0) -> 120 | L25: =I25+J25-K25 -> 1495.4879 | M25: =M24+L25 -> 17960.112 | N25: =L25/(1+'📋 Parametri'!C24)^22 -> 780.48392 | O25: =O24+N25 -> 9949.263 | P25: =L25 -> 1495.4879
A26: 23 | B26: ='📋 Parametri'!C5*'📋 Parametri'!C7*'📋 Parametri'!C6*'📋 Parametri'!C8*(1-'📋 Parametri'!C9)^(23-1) -> 5158.5811 | C26: =B26*'📋 Parametri'!C19 -> 2321.3615 | D26: =B26-C26 -> 2837.2196 | E26: ='📋 Parametri'!C17*(1+'📋 Parametri'!C20)^(23-1) -> 0.47902585 | F26: ='📋 Parametri'!C18*(1+'📋 Parametri'!C20)^(23-1) -> 0.19161034 | G26: =C26*E26 -> 1111.9922 | H26: =D26*F26 -> 543.64061 | I26: =G26+H26 -> 1655.6328 | J26: =IF(AND(23>=1,23<='📋 Parametri'!C23),'📋 Parametri'!C11*'📋 Parametri'!C22/'📋 Parametri'!C23,0) -> 0 | K26: ='📋 Parametri'!C13+IF(23='📋 Parametri'!C14,'📋 Parametri'!C15,0) -> 120 | L26: =I26+J26-K26 -> 1535.6328 | M26: =M25+L26 -> 19495.744 | N26: =L26/(1+'📋 Parametri'!C24)^23 -> 778.09245 | O26: =O25+N26 -> 10727.355 | P26: =L26 -> 1535.6328
A27: 24 | B27: ='📋 Parametri'!C5*'📋 Parametri'!C7*'📋 Parametri'!C6*'📋 Parametri'!C8*(1-'📋 Parametri'!C9)^(24-1) -> 5132.7882 | C27: =B27*'📋 Parametri'!C19 -> 2309.7547 | D27: =B27-C27 -> 2823.0335 | E27: ='📋 Parametri'!C17*(1+'📋 Parametri'!C20)^(24-1) -> 0.49339663 | F27: ='📋 Parametri'!C18*(1+'📋 Parametri'!C20)^(24-1) -> 0.19735865 | G27: =C27*E27 -> 1139.6252 | H27: =D27*F27 -> 557.15008 | I27: =G27+H27 -> 1696.7752 | J27: =IF(AND(24>=1,24<='📋 Parametri'!C23),'📋 Parametri'!C11*'📋 Parametri'!C22/'📋 Parametri'!C23,0) -> 0 | K27: ='📋 Parametri'!C13+IF(24='📋 Parametri'!C14,'📋 Parametri'!C15,0) -> 120 | L27: =I27+J27-K27 -> 1576.7752 | M27: =M26+L27 -> 21072.52 | N27: =L27/(1+'📋 Parametri'!C24)^24 -> 775.66894 | O27: =O26+N27 -> 11503.024 | P27: =L27 -> 1576.7752
A28: 25 | B28: ='📋 Parametri'!C5*'📋 Parametri'!C7*'📋 Parametri'!C6*'📋 Parametri'!C8*(1-'📋 Parametri'!C9)^(25-1) -> 5107.1242 | C28: =B28*'📋 Parametri'!C19 -> 2298.2059 | D28: =B28-C28 -> 2808.9183 | E28: ='📋 Parametri'!C17*(1+'📋 Parametri'!C20)^(25-1) -> 0.50819853 | F28: ='📋 Parametri'!C18*(1+'📋 Parametri'!C20)^(25-1) -> 0.20327941 | G28: =C28*E28 -> 1167.9449 | H28: =D28*F28 -> 570.99526 | I28: =G28+H28 -> 1738.9401 | J28: =IF(AND(25>=1,25<='📋 Parametri'!C23),'📋 Parametri'!C11*'📋 Parametri'!C22/'📋 Parametri'!C23,0) -> 0 | K28: ='📋 Parametri'!C13+IF(25='📋 Parametri'!C14,'📋 Parametri'!C15,0) -> 120 | L28: =I28+J28-K28 -> 1618.9401 | M28: =M27+L28 -> 22691.46 | N28: =L28/(1+'📋 Parametri'!C24)^25 -> 773.21481 | O28: =O27+N28 -> 12276.239 | P28: =L28 -> 1618.9401
A29: TOTALE | B29: =SUM(B4:B28) -> 135682.28 | C29: =SUM(C4:C28) -> 61057.026 | D29: =SUM(D4:D28) -> 74625.254 | G29: =SUM(G4:G28) -> 22091.279 | H29: =SUM(H4:H28) -> 10800.181 | I29: =SUM(I4:I28) -> 32891.46 | J29: =SUM(J4:J28) -> 6000 | K29: =SUM(K4:K28) -> 4200 | L29: =SUM(L4:L28) -> 34691.46 | N29: =SUM(N4:N28) -> 24276.239

Sheet 🏆 KPI & Scenari
B1: 🏆 KPI PRINCIPALI & ANALISI SCENARI
B3: INDICATORI CHIAVE (Scenario Principale)
B4: Produzione Anno 1 (kWh) | C4: ='📊 Modello Annuale'!B4 -> 5760
B5: Produzione Anno 25 (kWh) | C5: ='📊 Modello Annuale'!B28 -> 5107.1242
B6: Energia Totale 25 anni (MWh) | C6: ='📊 Modello Annuale'!B29/1000 -> 135.68228
B7: Investimento Totale | C7: ='📋 Parametri'!C11+'📋 Parametri'!C12 -> 12000
B8: Beneficio Lordo Totale | C8: ='📊 Modello Annuale'!I29 -> 32891.46
B9: Flusso Cumulato Anno 25 | C9: ='📊 Modello Annuale'!M28 -> 22691.46
B10: NPV (Valore Attuale Netto) | C10: ='📊 Modello Annuale'!O28 -> 12276.239
B11: IRR (Tasso Interno Rendimento) | C11: =IFERROR(IRR('📊 Modello Annuale'!P4:P28,0.1),"N/D") -> 0.12807382
B12: Payback Period (anni) | C12: =IFERROR(MATCH(TRUE(),'📊 Modello Annuale'!M4:M28>=0,0),">25") -> >25
B13: ROI Totale 25 anni | C13: =('📊 Modello Annuale'!I29+'📊 Modello Annuale'!J29-'📊 Modello Annuale'!K29-('📋 Parametri'!C11+'📋 Parametri'!C12))/('📋 Parametri'!C11+'📋 Parametri'!C12) -> 1.890955
B14: CO₂ Risparmiata (tonnellate) | C14: ='📊 Modello Annuale'!B29*0.233/1000 -> 31.613971
B15: Alberi Equivalenti | C15: ='📊 Modello Annuale'!B29*0.233/1000*50 -> 1580.6986
B18: ANALISI SCENARI — confronta diverse ipotesi (valori in BLU modificabili)
B19: Parametro | C19: Scenario Base | D19: Ottimistico | E19: Con Batteria | F19: Pessimistico
B20: Potenza (kWp) | C20: 6 | D20: 6 | E20: 6 | F20: 6
B21: Fattore Esposizione | C21: 1 | D21: 1 | E21: 1 | F21: 0.74
B22: Ore Picco (h/anno) | C22: 1350 | D22: 1500 | E22: 1350 | F22: 1150
B23: Performance Ratio | C23: 0.8 | D23: 0.83 | E23: 0.8 | F23: 0.76
B24: Degrado Annuo | C24: 0.005 | D24: 0.004 | E24: 0.005 | F24: 0.007
B25: Costo Impianto (€) | C25: 10200 | D25: 9500 | E25: 10200 | F25: 11000
B26: Costo Batteria (€) | C26: 0 | D26: 0 | E26: 5000 | F26: 0
B27: Prezzo Acquisto €/kWh | C27: 0.25 | D27: 0.28 | E27: 0.25 | F27: 0.22
B28: Autoconsumo % | C28: 0.4 | D28: 0.45 | E28: 0.7 | F28: 0.3
B29: Incr. Prezzo Energia | C29: 0.03 | D29: 0.06 | E29: 0.03 | F29: 0.01
B30: Detrazione IRPEF | C30: 0.5 | D30: 0.5 | E30: 0.5 | F30: 0
B32: RISULTATI SCENARI (calcolati)
B33: Metrica | C33: Scenario Base | D33: Ottimistico | E33: Con Batteria | F33: Pessimistico
B34: Produzione Anno 1 (kWh) | C34: ='🏆 KPI & Scenari'!C20*'🏆 KPI & Scenari'!C22*'🏆 KPI & Scenari'!C21*'🏆 KPI & Scenari'!C23 -> 6480 | D34: ='🏆 KPI & Scenari'!D20*'🏆 KPI & Scenari'!D22*'🏆 KPI & Scenari'!D21*'🏆 KPI & Scenari'!D23 -> 7470 | E34: ='🏆 KPI & Scenari'!E20*'🏆 KPI & Scenari'!E22*'🏆 KPI & Scenari'!E21*'🏆 KPI & Scenari'!E23 -> 6480 | F34: ='🏆 KPI & Scenari'!F20*'🏆 KPI & Scenari'!F22*'🏆 KPI & Scenari'!F21*'🏆 KPI & Scenari'!F23 -> 3880.56
B35: Investimento Totale (€) | C35: ='🏆 KPI & Scenari'!C25+'🏆 KPI & Scenari'!C26 -> 10200 | D35: ='🏆 KPI & Scenari'!D25+'🏆 KPI & Scenari'!D26 -> 9500 | E35: ='🏆 KPI & Scenari'!E25+'🏆 KPI & Scenari'!E26 -> 15200 | F35: ='🏆 KPI & Scenari'!F25+'🏆 KPI & Scenari'!F26 -> 11000
B36: Payback Approx. (anni) | C36: =IFERROR(('🏆 KPI & Scenari'!C25+'🏆 KPI & Scenari'!C26)/('🏆 KPI & Scenari'!C20*'🏆 KPI & Scenari'!C22*'🏆 KPI & Scenari'!C21*'🏆 KPI & Scenari'!C23*('🏆 KPI & Scenari'!C28*'🏆 KPI & Scenari'!C27+(1-'🏆 KPI & Scenari'!C28)*0.08)+'🏆 KPI & Scenari'!C25*'🏆 KPI & Scenari'!C30/10-120),">25") -> 7.5609322 | D36: =IFERROR(('🏆 KPI & Scenari'!D25+'🏆 KPI & Scenari'!D26)/('🏆 KPI & Scenari'!D20*'🏆 KPI & Scenari'!D22*'🏆 KPI & Scenari'!D21*'🏆 KPI & Scenari'!D23*('🏆 KPI & Scenari'!D28*'🏆 KPI & Scenari'!D27+(1-'🏆 KPI & Scenari'!D28)*0.08)+'🏆 KPI & Scenari'!D25*'🏆 KPI & Scenari'!D30/10-120),">25") -> 5.8465136 | E36: =IFERROR(('🏆 KPI & Scenari'!E25+'🏆 KPI & Scenari'!E26)/('🏆 KPI & Scenari'!E20*'🏆 KPI & Scenari'!E22*'🏆 KPI & Scenari'!E21*'🏆 KPI & Scenari'!E23*('🏆 KPI & Scenari'!E28*'🏆 KPI & Scenari'!E27+(1-'🏆 KPI & Scenari'!E28)*0.08)+'🏆 KPI & Scenari'!E25*'🏆 KPI & Scenari'!E30/10-120),">25") -> 9.0502048 | F36: =IFERROR(('🏆 KPI & Scenari'!F25+'🏆 KPI & Scenari'!F26)/('🏆 KPI & Scenari'!F20*'🏆 KPI & Scenari'!F22*'🏆 KPI & Scenari'!F21*'🏆 KPI & Scenari'!F23*('🏆 KPI & Scenari'!F28*'🏆 KPI & Scenari'!F27+(1-'🏆 KPI & Scenari'!F28)*0.08)+'🏆 KPI & Scenari'!F25*'🏆 KPI & Scenari'!F30/10-120),">25") -> 31.123708
B37: Beneficio Anno 1 (€) | C37: ='🏆 KPI & Scenari'!C20*'🏆 KPI & Scenari'!C22*'🏆 KPI & Scenari'!C21*'🏆 KPI & Scenari'!C23*('🏆 KPI & Scenari'!C28*'🏆 KPI & Scenari'!C27+(1-'🏆 KPI & Scenari'!C28)*0.08) -> 959.04 | D37: ='🏆 KPI & Scenari'!D20*'🏆 KPI & Scenari'!D22*'🏆 KPI & Scenari'!D21*'🏆 KPI & Scenari'!D23*('🏆 KPI & Scenari'!D28*'🏆 KPI & Scenari'!D27+(1-'🏆 KPI & Scenari'!D28)*0.08) -> 1269.9 | E37: ='🏆 KPI & Scenari'!E20*'🏆 KPI & Scenari'!E22*'🏆 KPI & Scenari'!E21*'🏆 KPI & Scenari'!E23*('🏆 KPI & Scenari'!E28*'🏆 KPI & Scenari'!E27+(1-'🏆 KPI & Scenari'!E28)*0.08) -> 1289.52 | F37: ='🏆 KPI & Scenari'!F20*'🏆 KPI & Scenari'!F22*'🏆 KPI & Scenari'!F21*'🏆 KPI & Scenari'!F23*('🏆 KPI & Scenari'!F28*'🏆 KPI & Scenari'!F27+(1-'🏆 KPI & Scenari'!F28)*0.08) -> 473.42832
B38: CO₂ Risparm. 25a (t) | C38: ='🏆 KPI & Scenari'!C20*'🏆 KPI & Scenari'!C22*'🏆 KPI & Scenari'!C21*'🏆 KPI & Scenari'!C23*25*0.233/1000 -> 37.746 | D38: ='🏆 KPI & Scenari'!D20*'🏆 KPI & Scenari'!D22*'🏆 KPI & Scenari'!D21*'🏆 KPI & Scenari'!D23*25*0.233/1000 -> 43.51275 | E38: ='🏆 KPI & Scenari'!E20*'🏆 KPI & Scenari'!E22*'🏆 KPI & Scenari'!E21*'🏆 KPI & Scenari'!E23*25*0.233/1000 -> 37.746 | F38: ='🏆 KPI & Scenari'!F20*'🏆 KPI & Scenari'!F22*'🏆 KPI & Scenari'!F21*'🏆 KPI & Scenari'!F23*25*0.233/1000 -> 22.604262

Sheet 📈 Grafici
A1: 📈 GRAFICI — I grafici si aggiornano automaticamente al variare dei parametri

Sheet 🔧 Tabelle Riferimento
B1: 🔧 TABELLE DI RIFERIMENTO — Valori da usare nei Parametri
B3: FATTORE ESPOSIZIONE (da inserire in C6) | E3: ORE PICCO PER ZONA (da inserire in C7)
B4: Sud | C4: 1 | E4: Nord Italia (Milano/Torino) | F4: 1150
B5: Sud-Est | C5: 0.97 | E5: Centro Italia (Roma/Firenze) | F5: 1350
B6: Sud-Ovest | C6: 0.97 | E6: Sud Italia (Napoli/Bari) | F6: 1500
B7: Est | C7: 0.74 | E7: Sicilia / Sardegna | F7: 1600
B8: Ovest | C8: 0.74
B9: Nord-Est | C9: 0.5
B10: Nord-Ovest | C10: 0.5
B11: Nord | C11: 0.4
B14: NOTE METODOLOGICHE
B15: 1. Produzione = Potenza(kWp) × OrePicco × FattoreEsposizione × PerformanceRatio × (1–Degrado)^(anno–1)
B16: 2. Beneficio = Autoconsumata × PrezzoAcquisto + Immessa × PrezzoVendita
B17: 3. Il prezzo energia cresce ogni anno al tasso 'Incremento annuo' (formula composta)
B18: 4. Incentivo IRPEF: il 50% del costo impianto viene detratto in quote uguali nei primi 10 anni
B19: 5. NPV = somma dei flussi annui attualizzati al tasso di sconto, al netto dell'investimento iniziale
B20: 6. IRR = tasso che rende NPV=0; confrontarlo con il rendimento di investimenti alternativi
B21: 7. Payback = anno in cui il flusso cumulato diventa positivo (valore approssimato al numero intero)
B22: 8. CO₂ risparmiata basata su fattore emissivo medio italiano 0.233 kg CO₂/kWh (fonte: ISPRA 2023)
